restack_get_started/__init__.py
restack_get_started/main.py
restackio_get_started-0.6.24.dist-info/METADATA
restackio_get_started-0.6.24.dist-info/WHEEL
restackio_get_started-0.6.24.dist-info/entry_points.txt
restackio_get_started-0.6.24.dist-info/RECORD
